{"results":[["Trait","1","2","3"],["Clockwork Heart--talents:3020121",75,167,259],["Clockwork Heart",77,166,253],["Heart of Darkness--talents:3020121",64,133,206],["Undulating Tides (25% Lockout per Min)--talents:3020121",89,174,259],["Undulating Tides--talents:3020121",101,203,307],["Undulating Tides (25% Lockout per Min)",85,174,258],["Undulating Tides",103,205,300],["Heart of Darkness",69,140,206],["Loyal to the End (4 Allies)--talents:3020121",74,154,223],["Loyal to the End--talents:3020121",39,75,116],["Loyal to the End (4 Allies)",70,150,215],["Seductive Power--talents:3020121",28,66,95],["Seductive Power",32,64,93],["Bonded Souls--talents:3020121",16,39,55],["Bonded Souls",19,32,57],["Treacherous Covenant--talents:3020121",58,115,173],["Treacherous Covenant",57,113,173],["Fight or Flight",30,57,89],["Endless Hunger--talents:3020121",84,161,245],["Fight or Flight--talents:3020121",29,63,93],["Endless Hunger",85,162,233],["Ancients' Bulwark--talents:3020121",84,162,240],["Ancients' Bulwark",85,160,237],["Apothecary's Concoctions--talents:3020121",47,103,145],["Apothecary's Concoctions",46,99,141],["Shadow of Elune--talents:3020121",38,71,93],["Shadow of Elune",33,70,91],["Laser Matrix--talents:3020121",54,105,153],["Laser Matrix",54,102,157],["Archive of the Titans--talents:3020121",28,58,89],["Archive of the Titans",31,55,87],["Relational Normalization Gizmo--talents:3020121",41,72,101],["Relational Normalization Gizmo",36,68,103],["Synaptic Spark Capacitor--talents:3020121",72,146,223],["Synaptic Spark Capacitor",69,142,223],["Ricocheting Inflatable Pyrosaw--talents:3020121",50,94,141],["Ricocheting Inflatable Pyrosaw",43,93,144],["Barrage Of Many Bombs--talents:3020121",96,179,268],["Barrage Of Many Bombs",94,179,266],["Training of Niuzao--talents:1020123",32,64,96],["Training of Niuzao",29,62,91],["Collective Will / Stand As One--talents:3020121",12,22,32],["Collective Will / Stand As One",11,18,34],["Combined Might / Stronger Together--talents:3020121",7,17,25],["Combined Might / Stronger Together",8,17,23],["Sylvanas' Resolve / Anduin's Dedication--talents:3020121",35,78,113],["Sylvanas' Resolve / Anduin's Dedication",31,74,110],["Battlefield Focus / Battlefield Precision--talents:3020121",53,93,128],["Battlefield Focus / Battlefield Precision",51,88,124],["Retaliatory Fury / Last Gift--talents:3020121",31,62,94],["Retaliatory Fury / Last Gift",30,57,88],["Glory in Battle / Liberator's Might",42,93,135],["Tidal Surge--talents:3020121",66,121,182],["Earthlink",15,24,35],["Azerite Globules",28,56,86],["Azerite Globules--talents:3020121",26,58,86],["Dagger in the Back--talents:3020121",46,76,117],["Dagger in the Back",42,80,114],["Blood Siphon",16,36,57],["Lifespeed",8,38,52],["Filthy Transfusion--talents:3020121",50,100,144],["Blood Siphon--talents:3020121",21,41,61],["Gutripper--talents:3020121",31,67,95],["Rezan's Fury--talents:3020121",63,123,179],["Heed My Call--talents:3020121",34,73,114],["Glory in Battle / Liberator's Might--talents:3020121",51,94,137],["Heed My Call",38,73,111],["Ruinous Bolt",36,75,112],["Incite the Pack--talents:3020121",50,105,147],["Filthy Transfusion",48,95,141],["Lifespeed--talents:3020121",0,38,55],["Meticulous Scheming--talents:3020121",46,87,116],["Blightborne Infusion--talents:3020121",82,143,197],["Tidal Surge",64,124,189],["Boiling Brew--talents:1020123",10,19,26],["Loyal to the End",33,73,111],["Boiling Brew",13,22,29],["Overwhelming Power",24,56,80],["Champion of Azeroth--talents:3020121",69,169,261],["On My Way--talents:3020121",24,51,72],["Rezan's Fury",61,118,179],["On My Way",22,52,77],["Unstable Catalyst--talents:3020121",27,64,97],["Champion of Azeroth",69,172,261],["Blood Rite",41,74,101],["Blightborne Infusion",82,142,191],["Thunderous Blast",56,107,158],["Earthlink--talents:3020121",16,26,36],["Gutripper",31,64,95],["Elusive Footwork",22,43,71],["Thunderous Blast--talents:3020121",57,107,160],["Swirling Sands--talents:3020121",68,128,169],["Incite the Pack",53,104,147],["Overwhelming Power--talents:3020121",24,58,83],["Ruinous Bolt--talents:3020121",42,75,111],["Unstable Flames",31,63,92],["Blood Rite--talents:3020121",41,81,113],["Elemental Whirl",27,51,77],["Unstable Flames--talents:3020121",31,68,95],["Meticulous Scheming",45,84,120],["Elusive Footwork--talents:1020123",27,54,84],["Secrets of the Deep",38,75,112],["Secrets of the Deep--talents:3020121",41,79,115],["Tradewinds",53,107,149],["Swirling Sands",70,123,171],["Elemental Whirl--talents:3020121",26,53,68],["Tradewinds--talents:3020121",56,108,145],["Unstable Catalyst",30,60,96]],"metas":{"fightLength":300,"fightLengthVariation":0.2,"targetError":0.2,"templateGear":["head=stygian_guise,id=174132,bonus_id=4824/1517/4775,azerite_powers=383/582/22/83/13","neck=heart_of_azeroth,id=158075,bonus_id=4929/5814/4936/1630,azerite_level=80","shoulders=gorak_tuls_mantle,id=159339,bonus_id=1647/4786/5480/4775,azerite_powers=384/193/459/87/13","back=ashjrakamas_shroud_of_resolve,id=169223,bonus_id=6286","chest=tortured_fleshbeast_cuirass,id=174136,bonus_id=4824/1517/4775,azerite_powers=116/582/31/85/13","wrists=bracers_of_dark_prophecy,id=174138,bonus_id=4824/1517","hands=grips_of_electrified_defense,id=159337,bonus_id=1674/5010/1637","waist=cincture_of_the_azerite_arsenal,id=159333,bonus_id=1674/5010/1637","legs=macabre_ritual_pants,id=174143,bonus_id=4824/1517/6550","feet=besiegers_deckstalkers,id=159320,bonus_id=1674/5010/1637/6552","finger1=ring_of_cosmic_potential,id=174533,bonus_id=4824/1517,enchant=accord_of_versatility","finger2=lord_waycrests_signet,id=158362,bonus_id=1674/5010/1637,enchant=accord_of_versatility","trinket1=writhing_segment_of_drestagath,id=173946,bonus_id=4824/1517","trinket2=psyche_shredder,id=174060,bonus_id=4824/1517","main_hand=qwor_nlyeth,id=174106,bonus_id=4824/1517/6550,enchant=versatile_navigation"],"templateTalents":[196607,0,325093,0,0,116847,196737],"templateDPS":2328,"elapsedTime":98.42,"totalEventsProcessed":4484512381,"totalIterations":436664,"totalActors":327,"simcBuildTimestamp":1605071478,"simcGitRevision":"c452495c02","wowVersion":"9.0.2.36532","wowBuild":36532}}