{"results":[["Trait","1","2","3"],["Clockwork Heart",122,244,366],["Heart of Darkness",98,191,291],["Undulating Tides (25% Lockout per Min)",87,169,261],["Undulating Tides",102,198,301],["Loyal to the End (4 Allies)",128,254,375],["Loyal to the End",66,130,193],["Seductive Power",63,122,189],["Bonded Souls",33,62,92],["Elemental Whirl",43,77,109],["Seismic Wave--talents:2332122",54,108,163],["Unstable Flames",46,95,133],["Seismic Wave",36,66,100],["Gathering Storm--talents:2332223",127,257,380],["Blood Siphon",39,71,110],["Test of Might",363,596,833],["Lord of War--talents:2332122",38,72,99],["Lord of War",55,106,165],["Combined Might / Stronger Together",15,32,40],["Synaptic Spark Capacitor",26,58,89],["Test of Might--talents:3332311",327,561,799],["Glory in Battle / Liberator's Might",72,132,190],["Thunderous Blast",55,108,158],["Tidal Surge",57,101,158],["Gathering Storm",2,4,3],["Secrets of the Deep",63,126,186],["Dagger in the Back",63,127,184],["Heed My Call",30,64,87],["Archive of the Titans",51,98,148],["Crushing Assault--talents:2332222",148,282,419],["Laser Matrix",56,100,151],["Crushing Assault",177,318,462],["Ancients' Bulwark",120,232,346],["Tradewinds",97,176,241],["Striking the Anvil",57,99,143],["Filthy Transfusion",59,102,156],["Blightborne Infusion",112,196,266],["Overwhelming Power",47,79,105],["Unstable Catalyst",53,104,158],["Sylvanas' Resolve / Anduin's Dedication",62,121,176],["Blood Rite",53,85,125],["Treacherous Covenant",97,192,283],["Ruinous Bolt",35,64,96],["Battlefield Focus / Battlefield Precision",63,127,185],["Shadow of Elune",49,88,122],["Champion of Azeroth",127,252,380],["Collective Will / Stand As One",25,47,69],["Endless Hunger",113,238,345],["Swirling Sands",92,167,231],["Gutripper",29,59,93],["Azerite Globules",23,34,52],["Apothecary's Concoctions",53,95,146],["Rezan's Fury",63,127,191],["Meticulous Scheming",59,104,137],["Lifespeed",26,47,72],["Retaliatory Fury / Last Gift",55,106,151],["Ricocheting Inflatable Pyrosaw",26,48,73],["Fight or Flight",29,56,86],["Earthlink",23,42,63],["Incite the Pack",88,173,242],["Barrage Of Many Bombs",44,84,120],["Striking the Anvil--talents:2332222",62,110,156],["Relational Normalization Gizmo",56,107,146]],"metas":{"fightLength":300,"fightLengthVariation":0.2,"targetError":0.2,"templateGear":["head=greathelm_of_phantasmic_reality,id=174167,bonus_id=4824/1517/4775,azerite_powers=226/582/21/83/13","neck=heart_of_azeroth,id=158075,bonus_id=4929/5814/4936/1630,azerite_level=80","shoulders=pauldrons_of_infinite_darkness,id=174166,bonus_id=4824/1517/4775,azerite_powers=226/582/31/83/13","back=ashjrakamas_shroud_of_resolve,id=169223,bonus_id=6286","chest=ashvane_wardens_cuirass,id=159440,bonus_id=1647/4775,azerite_powers=226/192/30/84/13","wrists=dragonbone_vambraces,id=174170,bonus_id=4824/1517/6475","hands=mirageweavers_gauntlets,id=174178,bonus_id=4824/1517/6476","waist=belt_of_muttering_truths,id=174174,bonus_id=4824/1517/6476","legs=living_obsidian_legguards,id=174172,bonus_id=4824/1517/6476","feet=boots_of_hallucinatory_reality,id=174173,bonus_id=4824/1517/6476","finger1=overclocking_bit_band,id=169159,bonus_id=1522/4778,enchant=accord_of_haste","finger2=logic_loop_of_recursion,id=169158,bonus_id=1522/4778,enchant=accord_of_haste","trinket1=ashvanes_razor_coral,id=169311,bonus_id=4800/1517/4786","trinket2=vitacharged_titanshard,id=174500,bonus_id=4824/1517/6448","main_hand=devastations_hour,id=172187,bonus_id=4824/1517,enchant=galeforce_striking"],"templateTalents":[260643,103827,202316,202163,262161,248621,152278],"templateDPS":2460,"elapsedTime":23.55,"totalEventsProcessed":1081530836,"totalIterations":262353,"totalActors":191,"simcBuildTimestamp":1605695889,"simcGitRevision":"87d6b273e0","wowVersion":"9.0.2.36639","wowBuild":36639}}