{"results":[["Trait","1","2","3"],["Clockwork Heart--talents:1300101",133,286,441],["Clockwork Heart",125,263,416],["Heart of Darkness--talents:1300101",127,254,370],["Swirling Sands",80,144,193],["Ruinous Bolt--talents:1300101",35,64,84],["Meticulous Scheming--talents:1300101",74,128,183],["Loyal to the End (4 Allies)--talents:1300101",199,393,583],["Endless Hunger",119,238,361],["Ricocheting Inflatable Pyrosaw--talents:1300101",39,86,126],["Meticulous Scheming",59,104,140],["Unstable Flames",40,75,113],["Secrets of the Deep",59,121,189],["Tidal Surge",49,97,142],["Endless Hunger--talents:1300101",145,293,438],["Unstable Catalyst--talents:1300101",63,136,205],["Avenger's Might--talents:1300101",254,496,708],["Rezan's Fury",56,101,145],["Unstable Catalyst",56,108,159],["Apothecary's Concoctions--talents:1300101",37,84,118],["Unstable Flames--talents:1300101",46,86,131],["Tradewinds--talents:1300101",147,275,376],["Filthy Transfusion",48,81,123],["Blightborne Infusion",97,154,211],["On My Way--talents:1300101",36,89,126],["Laser Matrix--talents:1300101",40,81,125],["Battlefield Focus / Battlefield Precision",34,59,95],["Elemental Whirl--talents:1300101",47,98,140],["Incite the Pack",96,197,276],["Loyal to the End (4 Allies)",149,289,445],["Undulating Tides--talents:1300101",89,173,253],["Elemental Whirl",35,71,111],["Empyrean Power",208,212,211],["Archive of the Titans",53,117,162],["Thunderous Blast--talents:1300101",42,92,140],["Combined Might / Stronger Together",13,29,39],["Filthy Transfusion--talents:1300101",31,84,118],["Earthlink--talents:1300101",32,53,87],["Apothecary's Concoctions",39,85,127],["Gutripper--talents:1300101",25,58,82],["Tidal Surge--talents:1300101",52,96,142],["Blood Rite",56,101,140],["Seductive Power--talents:1300101",86,173,271],["Dagger in the Back--talents:1300101",47,92,132],["Empyrean Power--talents:1300101",260,268,265],["Expurgation",61,122,183],["Sylvanas' Resolve / Anduin's Dedication--talents:1300101",82,156,237],["Light's Decree--talents:1300101",156,302,453],["Retaliatory Fury / Last Gift--talents:1300101",77,151,230],["Ricocheting Inflatable Pyrosaw",39,87,130],["Overwhelming Power",46,77,101],["Lifespeed",21,46,71],["Lifespeed--talents:1300101",36,65,90],["On My Way",41,72,106],["Blood Rite--talents:1300101",69,123,170],["Ruinous Bolt",35,59,92],["Shadow of Elune",51,81,116],["Tradewinds",108,197,280],["Earthlink",23,44,65],["Light's Decree",175,308,450],["Secrets of the Deep--talents:1300101",80,156,237],["Synaptic Spark Capacitor",60,122,178],["Champion of Azeroth--talents:1300101",171,338,517],["Undulating Tides",91,171,261],["Heed My Call",39,70,108],["Collective Will / Stand As One--talents:1300101",24,52,79],["Ancients' Bulwark",120,239,358],["Overwhelming Power--talents:1300101",47,94,129],["Rezan's Fury--talents:1300101",45,95,140],["Sylvanas' Resolve / Anduin's Dedication",63,123,182],["Azerite Globules--talents:1300101",26,43,70],["Treacherous Covenant",104,203,300],["Azerite Globules",26,50,71],["Indomitable Justice--talents:1300101",63,128,187],["Avenger's Might",148,289,411],["Champion of Azeroth",132,254,399],["Blightborne Infusion--talents:1300101",116,197,253],["Incite the Pack--talents:1300101",127,257,367],["Thunderous Blast",44,89,134],["Collective Will / Stand As One",16,44,65],["Heed My Call--talents:1300101",34,74,104],["Indomitable Justice",58,125,183],["Relentless Inquisitor",99,181,260],["Shadow of Elune--talents:1300101",57,114,149],["Seductive Power",67,135,197],["Combined Might / Stronger Together--talents:1300101",16,34,45],["Gutripper",30,51,90],["Barrage Of Many Bombs--talents:1300101",81,178,261],["Blood Siphon",39,80,124],["Undulating Tides (25% Lockout per Min)--talents:1300101",64,144,219],["Blood Siphon--talents:1300101",54,111,165],["Battlefield Focus / Battlefield Precision--talents:1300101",25,55,90],["Dagger in the Back",47,97,139],["Swirling Sands--talents:1300101",100,172,238],["Expurgation--talents:1300101",65,126,188],["Bonded Souls",27,53,71],["Relentless Inquisitor--talents:1300101",127,227,340],["Ancients' Bulwark--talents:1300101",154,292,451],["Undulating Tides (25% Lockout per Min)",74,148,224],["Retaliatory Fury / Last Gift",59,118,176],["Glory in Battle / Liberator's Might",54,111,160],["Glory in Battle / Liberator's Might--talents:1300101",72,143,200],["Loyal to the End--talents:1300101",97,189,297],["Bonded Souls--talents:1300101",32,71,97],["Barrage Of Many Bombs",88,175,262],["Relational Normalization Gizmo--talents:1300101",73,125,187],["Treacherous Covenant--talents:1300101",121,253,381],["Synaptic Spark Capacitor--talents:1300101",60,113,175],["Archive of the Titans--talents:1300101",73,133,207],["Relational Normalization Gizmo",57,109,149],["Fight or Flight--talents:1300101",76,158,237],["Laser Matrix",45,85,135],["Fight or Flight",55,104,153],["Loyal to the End",78,151,224],["Heart of Darkness",95,190,294]],"metas":{"fightLength":360,"fightLengthVariation":0.2,"targetError":0.2,"templateGear":["head=greathelm_of_phantasmic_reality,id=174167,bonus_id=4824/1517/4775,azerite_powers=125/396/21/13","neck=heart_of_azeroth,id=158075,bonus_id=4929/5814/4936/1630,azerite_level=80","shoulders=writhing_spaulders_of_madness,id=174165,bonus_id=4824/1517/4775,azerite_powers=125/187/459/13","back=ashjrakamas_shroud_of_resolve,id=169223,bonus_id=6286","chest=breastplate_of_twilight_decimation,id=174164,bonus_id=4824/1517/4775,azerite_powers=396/125/459/13","wrists=dragonbone_vambraces,id=174170,bonus_id=4824/1517/6547","hands=mirageweavers_gauntlets,id=174178,bonus_id=4824/1517","waist=dark_crystalline_girdle,id=174171,bonus_id=4824/1517/6550","legs=living_obsidian_legguards,id=174172,bonus_id=4824/1517/6553","feet=boots_of_hallucinatory_reality,id=174173,bonus_id=4824/1517","finger1=ring_of_cosmic_potential,id=174533,bonus_id=4824/1517,enchant=accord_of_critical_strike","finger2=ring_of_collective_consciousness,id=174530,bonus_id=4824/1517,enchant=accord_of_critical_strike","trinket1=ashvanes_razor_coral,id=169311,bonus_id=4800/1517","trinket2=vitacharged_titanshard,id=174500,bonus_id=4824/1517","main_hand=devastations_hour,id=172187,bonus_id=4824/1517,enchant=force_multiplier"],"templateTalents":[343527,326732,0,205191,223817,0,343721],"templateDPS":2650,"elapsedTime":178.72,"totalEventsProcessed":16389242398,"totalIterations":1467687,"totalActors":344,"simcBuildTimestamp":1605321369,"simcGitRevision":"cbc45d85e5","wowVersion":"9.0.2.36599","wowBuild":36599}}