{"results":[[1,"3020023","None","None",4136],[2,"3020022","None","None",4127],[3,"3030022","None","None",4063],[4,"2020022","None","None",4063],[5,"2020023","None","None",4061],[6,"3030023","None","None",4059],[7,"3010023","None","None",4039],[8,"3020021","None","None",4033],[9,"1020023","None","None",4017],[10,"3010022","None","None",4012],[11,"1020022","None","None",4001],[12,"3020032","None","None",3986],[13,"3010021","None","None",3961],[14,"2020021","None","None",3961],[15,"2030022","None","None",3957],[16,"2030023","None","None",3954],[17,"2010023","None","None",3950],[18,"3030021","None","None",3949],[19,"3020012","None","None",3947],[20,"3020033","None","None",3947],[21,"3020013","None","None",3937],[22,"1030023","None","None",3929],[23,"1020021","None","None",3915],[24,"1030022","None","None",3907],[25,"2010022","None","None",3903],[26,"1010023","None","None",3901],[27,"3030012","None","None",3900],[28,"2020012","None","None",3900],[29,"2020013","None","None",3890],[30,"3010012","None","None",3885],[31,"3010033","None","None",3884],[32,"2010021","None","None",3878],[33,"3010032","None","None",3875],[34,"2020032","None","None",3873],[35,"2030021","None","None",3865],[36,"3030013","None","None",3860],[37,"3010013","None","None",3860],[38,"2020033","None","None",3853],[39,"3030032","None","None",3845],[40,"3030033","None","None",3844],[41,"1020012","None","None",3843],[42,"1020013","None","None",3839],[43,"1020032","None","None",3837],[44,"1010021","None","None",3833],[45,"3020011","None","None",3830],[46,"1010022","None","None",3828],[47,"1030021","None","None",3822],[48,"3020031","None","None",3813],[49,"2010013","None","None",3810],[50,"2030012","None","None",3802],[51,"1020033","None","None",3796],[52,"2010032","None","None",3795],[53,"2020011","None","None",3785],[54,"2030013","None","None",3773],[55,"2010033","None","None",3771],[56,"2010012","None","None",3769],[57,"1010013","None","None",3767],[58,"1030012","None","None",3766],[59,"1030013","None","None",3762],[60,"1010012","None","None",3759],[61,"3010011","None","None",3759],[62,"1010033","None","None",3755],[63,"1010032","None","None",3739],[64,"2030032","None","None",3737],[65,"3010031","None","None",3731],[66,"2030033","None","None",3727],[67,"1020031","None","None",3725],[68,"3030031","None","None",3722],[69,"2020031","None","None",3716],[70,"1030032","None","None",3715],[71,"1020011","None","None",3710],[72,"3030011","None","None",3703],[73,"1030033","None","None",3701],[74,"2010011","None","None",3699],[75,"2030011","None","None",3682],[76,"1010011","None","None",3663],[77,"1010031","None","None",3649],[78,"1030011","None","None",3636],[79,"2030031","None","None",3624],[80,"2010031","None","None",3599],[81,"1030031","None","None",3589]],"metas":{"fightLength":300,"fightLengthVariation":0.2,"targetError":0.2,"templateGear":["head=gibbering_maw,id=174134,bonus_id=4824/1517/4775,azerite_powers=411/582/30/13","neck=heart_of_azeroth,id=158075,bonus_id=4929/5814/4936/1630,ilevel=145,azerite_level=80","shoulders=pauldrons_of_the_great_convergence,id=174133,bonus_id=4824/1517/4775,azerite_powers=411/582/21/13","back=ashjrakamas_shroud_of_resolve,id=169223,bonus_id=6286","chest=tortured_fleshbeast_cuirass,id=174136,bonus_id=4824/1517/4775,azerite_powers=180/582/31/13","wrists=bracers_of_dark_prophecy,id=174138,bonus_id=4824/1517/6573","hands=chitinspine_gloves,id=174137,bonus_id=4824/1517/6573","waist=belt_of_braided_vessels,id=174142,bonus_id=4824/1517/6573","legs=macabre_ritual_pants,id=174143,bonus_id=4824/1517/6573","feet=corpuscular_leather_greaves,id=174144,bonus_id=4824/1517/6573","finger1=ring_of_collective_consciousness,id=174530,bonus_id=4824/1517/6573,enchant=accord_of_critical_strike","finger2=ring_of_cosmic_potential,id=174533,bonus_id=4824/1517,enchant=accord_of_critical_strike","trinket1=ashvanes_razor_coral,id=169311,bonus_id=4800/1517","trinket2=deadeye_spyglass,id=159623,bonus_id=3536/4786/1637,ilevel=120","main_hand=unguent_caress,id=172197,bonus_id=4824/1517,enchant=deadly_navigation","off_hand=bilestained_crawg_tusks,id=159653,bonus_id=3536/4786/1637,ilevel=120,enchant=versatile_navigation"],"templateTalents":[196938,0,193531,0,0,193539,271877],"templateDPS":4059,"elapsedTime":6.29,"totalEventsProcessed":101823982,"totalIterations":38235,"totalActors":82,"simcBuildTimestamp":1602802461,"simcGitRevision":"ed8b7cfe73","wowVersion":"9.0.1.36200","wowBuild":36200}}