{"results":[["Essence","1","2","3"],["The Formless Void (Minor)--talents:1323121",36,53,69],["Nullification Dynamo (Minor)--talents:1113121",4,4,97],["Nullification Dynamo (Major)--talents:1113121",0,4,102],["Aegis of the Deep (Minor)--talents:1123121",73,79,78],["Aegis of the Deep (Major)--talents:1123121",78,78,71],["Anima of Life and Death (Minor)--talents:1123131",1,-5,1],["Anima of Life and Death (Major)--talents:1123131",81,92,90],["The Formless Void (Major)--talents:1323121",40,50,72],["Conflict and Strife (Minor)--talents:1123121",33,52,83],["Conflict and Strife (Major)--talents:1123121",35,58,85],["Memory of Lucid Dreams (Minor)--talents:1113111",26,27,65],["Memory of Lucid Dreams (Major)--talents:1113111",24,34,69],["Vision of Perfection (Major)--talents:1323121",19,25,56],["Ripple in Space (Minor)--talents:1113111",1,7,-2],["Ripple in Space (Major)--talents:1113111",67,86,90],["Vision of Perfection (Minor)--talents:1323121",7,5,33],["Worldvein Resonance (3 Allies) (Minor)--talents:1313121",62,85,103],["Worldvein Resonance (3 Allies) (Major)--talents:1313121",137,190,202],["Worldvein Resonance (Minor)--talents:1123121",10,20,36],["Worldvein Resonance (Major)--talents:1123121",69,141,155],["Vision of Perfection (Minor)",11,9,31],["Vision of Perfection (Major)",22,26,51],["Anima of Life and Death (Major)",71,78,76],["The Formless Void (Minor)",40,51,66],["The Crucible of Flame (Major)--talents:1123121",172,240,311],["Worldvein Resonance (3 Allies) (Minor)",62,90,100],["The Crucible of Flame (Major)",166,232,293],["Nullification Dynamo (Major)",-4,-4,95],["Ripple in Space (Major)",64,85,87],["Worldvein Resonance (3 Allies) (Major)",137,194,199],["Worldvein Resonance (Minor)",14,20,40],["Worldvein Resonance (Major)",70,142,154],["Memory of Lucid Dreams (Major)",27,30,65],["Ripple in Space (Minor)",-6,-5,-2],["Anima of Life and Death (Minor)",-3,-1,-4],["The Crucible of Flame (Minor)",102,133,194],["Conflict and Strife (Minor)",31,48,73],["The Crucible of Flame (Minor)--talents:1123121",106,139,212],["Memory of Lucid Dreams (Minor)",23,23,62],["Aegis of the Deep (Minor)",75,75,74],["Nullification Dynamo (Minor)",-3,-4,97],["Conflict and Strife (Major)",30,51,75],["Aegis of the Deep (Major)",72,77,79],["The Formless Void (Major)",39,51,69]],"metas":{"fightLength":360,"fightLengthVariation":0.2,"targetError":0.2,"templateGear":["head=gibbering_maw,id=174134,bonus_id=4824/1517/4775,azerite_powers=134/160/30/202/13","neck=heart_of_azeroth,id=158075,bonus_id=4929/5814/4936/1630,azerite_level=80","shoulders=gorak_tuls_mantle,id=159339,bonus_id=1647/4775,azerite_powers=134/193/459/202/13","back=ashjrakamas_shroud_of_resolve,id=169223,bonus_id=6286","chest=tortured_fleshbeast_cuirass,id=174136,bonus_id=4824/1517/4775,azerite_powers=134/582/31/85/13","wrists=bracers_of_dark_prophecy,id=174138,bonus_id=4824/1517/6550","hands=grips_of_electrified_defense,id=159337,bonus_id=4824/1637","waist=belt_of_braided_vessels,id=174142,bonus_id=4824/1517/6551","legs=macabre_ritual_pants,id=174143,bonus_id=4824/1517","feet=corpuscular_leather_greaves,id=174144,bonus_id=4824/1517","finger1=ring_of_cosmic_potential,id=174533,bonus_id=4824/1517,enchant=accord_of_versatility","finger2=ring_of_collective_consciousness,id=174530,bonus_id=4824/1517,enchant=accord_of_versatility","trinket1=vitacharged_titanshard,id=174500,bonus_id=4824/1517","trinket2=ashvanes_razor_coral,id=169311,bonus_id=4800/1517","main_hand=bilestained_crawg_tusks,id=159653,bonus_id=4824/1637,enchant=deadly_navigation","off_hand=bilestained_crawg_tusks,id=159653,bonus_id=4824/1637,enchant=versatile_navigation"],"templateTalents":[207550,227174,320331,263642,202138,321453,209258],"templateDPS":2059,"elapsedTime":92.74,"totalEventsProcessed":5272633994,"totalIterations":352794,"totalActors":139,"simcBuildTimestamp":1605599416,"simcGitRevision":"8985c8d0da","wowVersion":"9.0.2.36639","wowBuild":36639}}